qfnn/__init__.py
qfnn/qf_circ/__init__.py
qfnn/qf_circ/base.py
qfnn/qf_circ/f_lyr_circ.py
qfnn/qf_circ/gates.py
qfnn/qf_circ/n_lyr_circ.py
qfnn/qf_circ/p_lyr_circ.py
qfnn/qf_circ/u_lyr_circ.py
qfnn/qf_circ/v_lyr_circ.py
qfnn/qf_fb/__init__.py
qfnn/qf_fb/c_input.py
qfnn/qf_fb/c_mnist.py
qfnn/qf_fb/c_qf_mixer.py
qfnn/qf_fb/q_input.py
qfnn/qf_fb/q_output.py
qfnn/qf_map/__init__.py
qfnn/qf_map/u_lyr_map.py
qfnn/qf_net/__init__.py
qfnn/qf_net/b_lyr.py
qfnn/qf_net/n_lyr.py
qfnn/qf_net/p_lyr.py
qfnn/qf_net/u_lyr.py
qfnn/qf_net/utils.py
qfnn/qf_net/v_lyr.py
qfnn-0.1.23.dist-info/LICENSE
qfnn-0.1.23.dist-info/METADATA
qfnn-0.1.23.dist-info/WHEEL
qfnn-0.1.23.dist-info/top_level.txt
qfnn-0.1.23.dist-info/RECORD
