Metadata-Version: 2.1
Name: qfnn
Version: 0.1.23
Summary: A library to support QuantumFlow series works
Home-page: https://jqub.ece.gmu.edu/categories/QF/
Author: Weiwen Jiang, Zhirui Hu
Author-email: wjiang8@gmu.edu
License: UNKNOWN
Project-URL: Bug Tracker, https://github.com/weiwenjiang/QuantumFlow_Tutorial/issues
Platform: UNKNOWN
Classifier: Programming Language :: Python :: 3
Classifier: License :: OSI Approved :: MIT License
Classifier: Operating System :: OS Independent
Requires-Python: >=3.6
License-File: LICENSE
